mondossierweb/__init__.py
mondossierweb/main.py
mondossierweb-0.1.2.dist-info/METADATA
mondossierweb-0.1.2.dist-info/WHEEL
mondossierweb-0.1.2.dist-info/entry_points.txt
mondossierweb-0.1.2.dist-info/RECORD
