Metadata-Version: 2.1
Name: mondossierweb
Version: 0.1.2
Summary: Parses grades out of mondossierweb[1;5D[1;5D[1;5D
License: MIT
Author: Ewen Le Bihan
Author-email: hey@ewen.works
Requires-Python: >=3.10,<4.0
Classifier: License :: OSI Approved :: MIT License
Classifier: Programming Language :: Python :: 3
Classifier: Programming Language :: Python :: 3.10
Classifier: Programming Language :: Python :: 3.11
Requires-Dist: bs4 (>=0.0.1,<0.0.2)
Requires-Dist: docopt (>=0.6.2,<0.7.0)
Requires-Dist: helium (>=3.0.9,<4.0.0)
Requires-Dist: lxml (>=4.9.2,<5.0.0)
